simple_parameters/.gitignore
simple_parameters/README.md
simple_parameters/setup.py
simple_parameters/simple_parameters.json
simple_parameters/simple_parameters.py
simple_parameters-1.6.dist-info/METADATA
simple_parameters-1.6.dist-info/WHEEL
simple_parameters-1.6.dist-info/top_level.txt
simple_parameters-1.6.dist-info/RECORD
