Metadata-Version: 2.1
Name: simple-parameters
Version: 1.6
Summary: Simple command line parameter parser
Home-page: https://github.com/crazybusy/simple_parameters
Author: crazybusy
Author-email: UNKNOWN
License: UNKNOWN
Platform: UNKNOWN
